{"links": ["https://drive.uc.cn/s/3b50ba305fd94", "https://115cdn.com/s/swfxbz83zrk?password=t58d", "https://pan.quark.cn/s/a8fea550b158", "https://pan.baidu.com/s/1f2bO1NXQ06xGLbxSc60UVw?pwd=bf8b", "https://pan.baidu.com/s/1BUbGzX1zu5RpAeMwBY2KKQ?pwd=qsxu", "https://cloud.189.cn/t/vMnEnefmuy6f", "https://115cdn.com/s/swfxbzx3zrk?password=t58d", "https://pan.baidu.com/s/1pn94_T-WUoy1aa87usvWLg?pwd=n6a4", "https://pan.quark.cn/s/9c3202f0798f", "https://cloud.189.cn/t/fI7vE3fYRVNb", "https://pan.quark.cn/s/62ddda63a697", "https://pan.quark.cn/s/60ab5a5f689d", "https://pan.baidu.com/s/1EPdX89tn6ZKIuozatWyQQg?pwd=admd", "https://pan.quark.cn/s/5ed25317a37c"], "sizes": [8076097, 18537734, 41135527, 25623223, 14836270, 214030, 12679025, 15556821, 16763735, 12938617, 1061950, 17442943], "chat_forward_count_msg_id": {"qfsy_tgsearch": 113703}, "today_count": 14, "today": "2026-04-23", "bot_links": {}}