{"links": ["https://pan.baidu.com/s/161hhX8nuBJlGlNmvpKo59A?pwd=3wm1", "https://pan.baidu.com/s/1OQDixy3ZvxkFjNnpRzpwaw?pwd=4q8i", "https://pan.quark.cn/s/91722adf7858", "https://pan.quark.cn/s/e3ed483d51c2", "https://pan.quark.cn/s/5b2aec7d38fb", "https://pan.quark.cn/s/3660d3b48750", "https://www.alipan.com/s/iEnqtyiRc3L", "https://pan.quark.cn/s/98939f11a1a3", "https://pan.baidu.com/s/1uFjpjTGJqpHgaBl1VTUsuw?pwd=x6jr", "https://cloud.189.cn/t/IfIVFjqAzuQr", "https://pan.quark.cn/s/b97c47c0f661", "https://pan.quark.cn/s/b41e8ab50a7e", "https://cloud.189.cn/t/Z7BbmyNr6n22"], "sizes": [57524], "chat_forward_count_msg_id": {"qfsy_tgsearch": 48789}, "today_count": 13, "today": "2025-07-17", "bot_links": {}}