{"links": ["https://pan.quark.cn/s/118e058ea713", "https://www.alipan.com/s/csHs3YTEuPH", "https://pan.quark.cn/s/242511b4833c", "https://pan.quark.cn/s/9da2b3d8393c", "https://pan.quark.cn/s/3241fe8bc53f", "https://pan.quark.cn/s/6960559f276e", "https://cloud.189.cn/t/naQfQ3UrQRni", "https://pan.quark.cn/s/fdb6758359db", "https://pan.baidu.com/s/15ZZKOAV6P4BpDzn5Ns7Rww?pwd=vq1j", "https://pan.quark.cn/s/a1c257265878", "https://cloud.189.cn/t/FNZfIn7ramIz", "https://www.alipan.com/s/c8zwC7S7X5Z", "https://pan.quark.cn/s/23c652281be3", "https://pan.quark.cn/s/4a4c39ae4200", "https://pan.quark.cn/s/767854b48856", "https://pan.quark.cn/s/972fc6ec3d25", "https://pan.quark.cn/s/178e4095885e", "https://pan.quark.cn/s/354b55fc28e3", "https://pan.quark.cn/s/c34748a3ccca", "https://pan.quark.cn/s/0f835e45b0a6", "https://pan.quark.cn/s/ca415d81ede4", "https://pan.baidu.com/s/1qSecdB9JzqIPHjkn7WTKdQ?pwd=66nC", "https://pan.quark.cn/s/19c2f8326ac4", "https://pan.quark.cn/s/a747484b7af9", "https://pan.baidu.com/s/1W0xtsP9Ze7nyOckzvZUDdg?pwd=Qx63", "https://pan.quark.cn/s/7b5b07401d97", "https://pan.baidu.com/s/1JIqjhsVZQBJjKOsB8OczqA?pwd=Yu66", "https://pan.baidu.com/s/1STZhO-vFnkxXBNc8QZoKwQ?pwd=e2gh", "https://pan.quark.cn/s/3ec99dab58f5", "https://pan.quark.cn/s/f0fa65f60ff1", "https://pan.baidu.com/s/185TUYvonJi17WwvUxD03aA?pwd=h94u", "https://www.alipan.com/s/NMNNWssv3bo", "https://www.alipan.com/s/jC9k5Jyntdd", "https://pan.quark.cn/s/811179c5495e", "https://pan.quark.cn/s/3d7a342cadf3", "https://pan.baidu.com/s/1oUTaGBwmI5NKS01_KDmXOw?pwd=f7v9", "https://pan.baidu.com/s/1URZuiqXDHeKBp38YHYUziQ?pwd=qwx5", "https://pan.quark.cn/s/3d8526499c8b", "https://pan.quark.cn/s/fe8a5cca086d", "https://pan.quark.cn/s/9927e23cc988", "https://pan.baidu.com/s/1wHemhdRzYWjYqBbeXfIaRg?pwd=1119", "https://pan.quark.cn/s/6780e3ab6e47", "https://pan.quark.cn/s/60d42e7d9fa7", "https://pan.quark.cn/s/310c270c194f", "https://pan.quark.cn/s/deeb3468ac94", "https://pan.quark.cn/s/ea2e109fa819", "https://pan.baidu.com/s/1bSyo315qBsSH2wIxMyru7w?pwd=Q9L6", "https://pan.baidu.com/s/1KFGYw9SuMvnAl1N71rqZPA?pwd=9A6G", "https://pan.quark.cn/s/69404733cd18", "https://www.alipan.com/s/mDmf2dcWJTY", "https://cloud.189.cn/t/2imArqIJFBrm", "https://pan.baidu.com/s/1TP6fkIkVDeqbcIremzF-Lw?pwd=s61m", "https://www.123684.com/s/IpPUVv-llDj?pwd=JZMM", "https://pan.quark.cn/s/d56df4a06b9e", "https://pan.quark.cn/s/515ff72f8407", "https://pan.quark.cn/s/54a8361b2c7a", "https://pan.baidu.com/s/1iqP_XF6VydOpDfAXKnx0JQ?pwd=Yu66", "https://pan.baidu.com/s/1ZqOwFuFLVir6YO-_HJHivg?pwd=ajva", "https://pan.quark.cn/s/ecb3a8555901", "https://pan.quark.cn/s/67cebb94d842", "https://www.alipan.com/s/MG4auyteumr", "https://pan.quark.cn/s/6f29347ff00a", "https://www.123684.com/s/u9izjv-mXUWv", "https://pan.quark.cn/s/f27d4052c9ff", "https://pan.quark.cn/s/7276a417bac0", "https://pan.quark.cn/s/b93b1d4bcaf5", "https://cloud.189.cn/t/3yU7jqFn6FZj", "https://cloud.189.cn/t/77jeu2vieM73", "https://pan.baidu.com/s/1AU_vRdws9Cs9sDGU1OMRwA?pwd=h2by", "https://pan.quark.cn/s/cbbb3904b682", "https://pan.quark.cn/s/6ba3337b3d4d", "https://pan.quark.cn/s/6b653ba35ed0", "https://pan.baidu.com/s/1lJaS7JwMPSKzTSKNpFq7IQ?pwd=Yu66", "https://pan.quark.cn/s/76ad36b09132", "https://pan.xunlei.com/s/VOdpZCH2lLDpBP-idsbv-M7XA1?pwd=2tmr#", "https://pan.quark.cn/s/f1d221602aa6", "https://pan.baidu.com/s/1JF5kVtbFybjHbNdWls96cw?pwd=2ag6", "https://pan.quark.cn/s/153f44887f16", "https://cloud.189.cn/t/NnYVriuyiuui", "https://www.alipan.com/s/cw6SbhRPs7v", "https://pan.quark.cn/s/660987d3bca2", "https://pan.quark.cn/s/abbb5673f266", "https://pan.quark.cn/s/8c0dcb1c1bad", "https://pan.quark.cn/s/c560f342cf8b", "https://cloud.189.cn/t/bYbAbaeInIJv", "https://www.123684.com/s/u9izjv-4TUWv", "https://pan.quark.cn/s/f2f0a5af680b", "https://pan.baidu.com/s/1c6gqUk9GgVBjbIUJATuEQQ?pwd=1119", "https://pan.quark.cn/s/517379fcdff6"], "sizes": [], "chat_forward_count_msg_id": {"qfsy_tgsearch": 80831}, "today_count": 89, "today": "2025-11-19", "bot_links": {"get_link_7275802881_1763476309_aliyun": "https://www.alipan.com/s/MG4auyteumr", "get_link_7275802881_1763476683_aliyun": "https://www.alipan.com/s/NMNNWssv3bo", "get_link_7181405369_1763480487_quark": "https://pan.quark.cn/s/abbb5673f266", "get_link_7181405369_1763480487_baidu": "https://pan.baidu.com/s/1rjVwu89vuCjhnpkbKw2ZFA?pwd=u4ze", "get_link_7181405369_1763480487_aliyun": "https://www.alipan.com/s/csHs3YTEuPH", "get_link_7181405369_1763481409_quark": "https://pan.quark.cn/s/0f835e45b0a6", "get_link_7181405369_1763481409_baidu": "https://pan.baidu.com/s/1P-JY-VQVKBpiVX1tOQKBsg?pwd=2won", "get_link_7181405369_1763481409_aliyun": "https://www.alipan.com/s/cw6SbhRPs7v", "get_link_7181405369_1763482105_quark": "https://pan.quark.cn/s/3d7a342cadf3", "get_link_7181405369_1763482105_baidu": "https://pan.baidu.com/s/1VTsGmgC94OL7njpvAGuMmw?pwd=59p8", "get_link_7181405369_1763482105_aliyun": "https://www.alipan.com/s/jC9k5Jyntdd", "get_link_7801995474_1763512643_quark": "https://pan.quark.cn/s/242511b4833c", "get_link_7801995474_1763512643_baidu": "https://pan.baidu.com/s/1iqP_XF6VydOpDfAXKnx0JQ?pwd=Yu66", "get_link_7801995474_1763512643_xunlei": "https://pan.xunlei.com/s/VOdntiWL96Pf2pJbcawDgAxjA1?pwd=wfjs", "get_link_7801995474_1763513161_quark": "https://pan.quark.cn/s/c34748a3ccca", "get_link_7801995474_1763513161_baidu": "https://pan.baidu.com/s/1JIqjhsVZQBJjKOsB8OczqA?pwd=Yu66", "get_link_7801995474_1763513161_xunlei": "https://pan.xunlei.com/s/VOeFSJhytKW9jmGXQN3xNh1bA1?pwd=8cy7", "get_link_7801995474_1763513810_quark": "https://pan.quark.cn/s/517379fcdff6", "get_link_7801995474_1763513810_baidu": "https://pan.baidu.com/s/1lJaS7JwMPSKzTSKNpFq7IQ?pwd=Yu66", "get_link_7801995474_1763513810_xunlei": "https://pan.xunlei.com/s/VOdpaaujTEapLp4aoRzzrzDlA1?pwd=8vru"}}