{"links": ["https://pan.quark.cn/s/ce937c0d287e", "https://www.alipan.com/s/2pu6AcajV25", "https://pan.quark.cn/s/291bfaa894df", "https://pan.quark.cn/s/f9a5616c8288", "magnet:?xt=urn:btih:83a2a90177a02448f2cff55850bfd7faf7c0de97", "https://pan.baidu.com/s/1TX9I-PfOkxfwReFoxW_bkg?pwd=bws2", "https://pan.baidu.com/s/1TRARxa-pPoNCf1lLE2IzEg?pwd=3awu", "https://pan.quark.cn/s/efe7810e1b07", "https://www.alipan.com/s/genVj2VsnF1", "https://pan.baidu.com/s/1gUo6ER-0tfsqBQciQKcR1Q?pwd=p84e", "https://pan.quark.cn/s/fba0156e547c", "https://pan.quark.cn/s/77e9a1ae71a9"], "sizes": [9695919, 10731961, 36871110, 98409933, 29375438, 367093593, 33120, 16785639, 304389740, 22785008, 18690163, 65545332], "chat_forward_count_msg_id": {"qfsy_tgsearch": 106746}, "today_count": 12, "today": "2026-03-22", "bot_links": {}}