{"links": ["https://cloud.189.cn/t/amUVriRruMBv", "https://pan.quark.cn/s/30d32430944a", "https://www.123pan.com/s/IpPUVv-1bDj?pwd=JZMM", "https://pan.baidu.com/s/1JrbObyU7FuDbUzqaamcwvg?pwd=ije2", "https://pan.quark.cn/s/515ff72f8407", "https://pan.quark.cn/s/5dc180d95214", "https://pan.baidu.com/s/1SuKvPYb1CPXhrYdJRiGnQQ?pwd=vsv6", "https://pan.quark.cn/s/31cf1cf78cda", "https://pan.quark.cn/s/a8170fc4708e", "https://www.alipan.com/s/ZRMqnaWuxo8", "https://115cdn.com/s/sww0ye336dh?password=f0f2", "magnet:?xt=urn:btih:0ca46f8d2044a83d477fe0bc111180a226ba3d1c", "https://pan.baidu.com/s/1dRFb939wKKAPnZ7eqiNy3A?pwd=96fm", "https://pan.quark.cn/s/21e242f1845e", "https://pan.quark.cn/s/3b8f78309216", "https://pan.quark.cn/s/3b4a04baedf5", "https://www.123684.com/s/u9izjv-TauWv", "https://pan.quark.cn/s/d51cb174f525", "https://pan.quark.cn/s/0985c5711463", "https://pan.quark.cn/s/4d15b434328b", "https://cloud.189.cn/t/Fbmm6rqeqAzy", "https://pan.quark.cn/s/f9775fa15092", "https://pan.baidu.com/s/1LqGf12atGHRMI2MZS7j_gg?pwd=xgcv", "https://www.alipan.com/s/cw6SbhRPs7v", "https://pan.quark.cn/s/02d1b1736ece", "https://pan.quark.cn/s/c5742110b3c2", "https://pan.quark.cn/s/eb6a27526546", "https://pan.quark.cn/s/52ca74fd4385", "https://pan.quark.cn/s/924ac6582548", "https://pan.quark.cn/s/99ba1fb26c32", "https://pan.quark.cn/s/5f07eda56bec", "https://cloud.189.cn/t/jqYVFnjuq2e2", "magnet:?xt=urn:btih:f549f3c5f3241e9301a5ea96b117be9df118baa5", "https://pan.quark.cn/s/f7260fff1a32", "https://pan.quark.cn/s/768dac2a53cf", "https://pan.quark.cn/s/59797ecd6ef9", "https://www.123pan.com/s/IpPUVv-fbDj?pwd=JZMM", "https://pan.baidu.com/s/1p7cseGubu9ReyYwA633YZg?pwd=76ws", "https://www.123684.com/s/IpPUVv-U8Dj?pwd=JZMM", "https://pan.quark.cn/s/d096fb764cbe", "https://pan.quark.cn/s/5aa85aee7ccc", "https://pan.quark.cn/s/86ccbd583ea1", "magnet:?xt=urn:btih:e0466300c1ac37d4444835bfd8386e3bfefffd2a", "https://drive.uc.cn/s/8fcfce7c1bb04?public=1", "https://pan.quark.cn/s/cffd3b6fc9a9", "https://pan.baidu.com/s/16iESCfhkvYS9x8eVGlIdFw?pwd=pyxf", "magnet:?xt=urn:btih:00608eb7b640db4fa7f852b22a1fa4efc2bf4b5e", "magnet:?xt=urn:btih:6f5305fd268ad8b73a7003b05c05e3e7a3fddfe8", "https://pan.quark.cn/s/4a7fbb50db2a", "https://pan.quark.cn/s/d098e86ef000", "https://www.123684.com/s/IpPUVv-huDj?pwd=JZMM", "https://pan.quark.cn/s/3f50b7a3a623", "https://pan.quark.cn/s/a7800a1a6878", "https://pan.baidu.com/s/1MMpqtAJXA2bDuB1RS-bnDA?pwd=yd5p", "https://caiyun.139.com/m/i?105Cpi1UDnKve", "https://cloud.189.cn/t/eauYNnfQzq2i", "https://pan.quark.cn/s/d3246fb41ba1", "https://www.123684.com/s/IpPUVv-ulDj?pwd=JZMM", "https://pan.baidu.com/s/1ZZ00VdqX9MItjmaXwjgK3A?pwd=e1gn", "https://pan.baidu.com/s/1hWWfZ-O6ml4cVsErG4tr0Q?pwd=my1b", "https://pan.quark.cn/s/f8d487bf3389", "https://pan.quark.cn/s/2ff21b8cfbdb", "https://pan.quark.cn/s/b93f94ad43da", "https://pan.quark.cn/s/dee2ea000faf", "https://pan.quark.cn/s/c2632975a870", "https://pan.quark.cn/s/3028c17dedd1", "https://pan.baidu.com/s/1dTGJjMevD_5PztdUzwmdvQ?pwd=vD3o", "https://pan.quark.cn/s/2d641047c29e", "https://pan.quark.cn/s/89d68604e6e3", "https://pan.baidu.com/s/1KIHqnGo1oazLRygkNT60Rw?pwd=0628", "https://cloud.189.cn/t/MvMJziBBn6Bj", "https://pan.quark.cn/s/444290672b67"], "sizes": [192514, 200323, 192901, 669844, 20448407, 499114, 198700, 159546, 38171843, 2989385, 198995, 2623711, 485215, 1436641, 856812, 896749, 12396, 18690924, 587257, 929402, 7163, 558589], "chat_forward_count_msg_id": {"qfsy_tgsearch": 79439}, "today_count": 72, "today": "2025-11-14", "bot_links": {"cl_qixingzhenren": "https://t.me/aibox2048_bot?start=cl_qixingzhenren"}}