{"links": ["https://pan.baidu.com/s/1M4g-nd_TxI36BkG2N1Emgg?pwd=7bw3", "https://pan.quark.cn/s/d7ca9e219453", "https://pan.baidu.com/s/1Ae9ePAbygJlF_PV_YL8Rhg?pwd=viux", "https://pan.baidu.com/s/1nfFeKdso6qUQB2aW3bFp6w?pwd=8bky", "https://pan.baidu.com/s/1Gm2b7MZ0H6TKElxxr6U2qg?pwd=jrkf", "https://pan.quark.cn/s/1843a76f43f7?pwd=iqCE", "https://pan.quark.cn/s/f0f72a6d2a44", "https://cloud.189.cn/t/Mv6zuajqI3yu", "https://115cdn.com/s/swfmz0h3zrk?password=d935#", "https://drive.uc.cn/s/24e36ec1b4a34", "https://pan.baidu.com/s/1vkSziBqedTrTMBuqb4GVDw?pwd=L9vG", "https://115cdn.com/s/swfm6b23hsv?password=bill#", "https://pan.quark.cn/s/2d4a40212382", "https://115cdn.com/s/swfmwuy3zwe?password=o6d8&#\u8bbf\u95ee\u7801\uff1ao6d8", "https://pan.quark.cn/s/b08cdb45f2c0", "https://115cdn.com/s/swfmzcx3zrk?password=t58d#", "https://pan.quark.cn/s/54defbbf3792", "https://pan.baidu.com/s/1g7B5FqCmiv6zipqh7aHibQ?pwd=6666", "https://www.alipan.com/s/y4eKywnMQas", "https://drive.uc.cn/s/b099a6aec6e14", "https://pan.quark.cn/s/eeffdda33e14", "https://pan.quark.cn/s/562d1bd7dae0", "https://pan.baidu.com/s/11OY6349-KjHPu0Y0mUahtA?pwd=cfe7", "https://pan.quark.cn/s/53b53faf28db", "https://pan.baidu.com/s/1-bpfsGhcYHzgSF9fVgUVvQ?pwd=FZt4", "https://pan.quark.cn/s/e764fc7d6523", "https://pan.baidu.com/s/1YJTdCFTg7ijvHaU_uC3qvA?pwd=mnfg", "https://pan.quark.cn/s/88e8f9837d8c", "https://pan.quark.cn/s/de546e2ce44d", "https://www.alipan.com/s/QwykTFqidUe", "https://pan.quark.cn/s/15aefdad6c1f", "https://pan.quark.cn/s/ef054963d266", "https://pan.baidu.com/s/1UOxrf1uySl__uZrxxxYm5A?pwd=X3Y2", "https://pan.baidu.com/s/1W_nfGQ2hyfzSt-iznLkHDg?pwd=pfe3", "https://pan.baidu.com/s/1JvTsu24oFbX2HkMC_8Ozmg?pwd=q98r", "https://pan.quark.cn/s/fda78292f04d", "https://pan.quark.cn/s/87f6c1bc3f86", "https://cloud.189.cn/t/BZfmqmyIrmMj", "https://115cdn.com/s/swfmw263zwe?password=o891&#\u8bbf\u95ee\u7801\uff1ao891", "https://pan.quark.cn/s/b89f654bfc8a", "https://drive.uc.cn/s/e5c6377c8f9b4", "https://115cdn.com/s/swfmw2t3zwe?password=s400&#\u8bbf\u95ee\u7801\uff1as400", "https://pan.quark.cn/s/7b2fab812404", "https://pan.quark.cn/s/184ae3bb2846", "https://pan.baidu.com/s/14-ThDJihEGj_BZrFPaVhXw?pwd=tunu", "https://pan.xunlei.com/s/VOm9KS-KJMb42Jw18G98xmfQA1?pwd=pxb2#", "https://pan.quark.cn/s/348146a9a6bc", "https://pan.quark.cn/s/e077f4b1839c", "https://115cdn.com/s/swfmwuc3zwe?password=s550&#\u8bbf\u95ee\u7801\uff1as550", "https://drive.uc.cn/s/ccf8ae4b56444?public=1", "https://pan.baidu.com/s/1-lwTt7rRoRHZE3bzlTibSA?pwd=QR93", "https://pan.baidu.com/s/1DA50ZP6vdI1PBLSMJ33Hvw?pwd=7u8s", "https://pan.xunlei.com/s/VOmHRmUGHfBtV054OqKgBtPWA1?pwd=kjvx#", "https://pan.quark.cn/s/44e99514f9d7", "https://www.123684.com/s/kyeA-NM5rv?pwd=ZY4K", "https://pan.quark.cn/s/808c232b8f4d", "https://cloud.189.cn/t/bYBbma2yIZ3e", "https://pan.quark.cn/s/6341b2d5355d?pwd=3ADJ", "https://pan.quark.cn/s/f5cb7e10dd77", "https://pan.xunlei.com/s/VOl1Hzixc-cqSccKcOC-n_ROA1?pwd=ufrr#", "https://drive.uc.cn/s/57cf286039494", "https://www.alipan.com/s/6QgDd6DizCi", "https://115cdn.com/s/swfmz0s3zrk?password=eb44#", "https://pan.quark.cn/s/2f3ca0c337bd", "https://pan.baidu.com/s/1bUjPoijavP2y16_B4NlkQg?pwd=1111", "https://pan.baidu.com/s/1bbekm6rKwE5cU_gdPTxpRw?pwd=iths", "https://pan.quark.cn/s/dc9944909425", "https://pan.xunlei.com/s/VOm4Jhuhc1Aufw_pDGNRdvHcA1?pwd=m367#", "https://cloud.189.cn/t/IJnuIfVZVVFf", "https://www.alipan.com/s/aRrTxYhTevV", "https://www.123912.com/s/IpPUVv-AhKj?pwd=Ocat", "https://pan.quark.cn/s/ca26cabec725", "https://pan.baidu.com/s/1EPIPlcGHsB010fYVjUfdrw?pwd=wm8h", "https://cloud.189.cn/t/y2ER32MfAnMz", "https://pan.quark.cn/s/ec83ce1f9ed2", "https://pan.quark.cn/s/4d3f1e94ae9e", "https://pan.quark.cn/s/eb89f5f82d05", "https://pan.quark.cn/s/6436eb7f9abb"], "sizes": [19927043, 17795, 16805958, 12262478, 16233520, 28332049, 88318546, 131948625, 9062006, 33966423, 12280923, 76678014], "chat_forward_count_msg_id": {"qfsy_tgsearch": 102221}, "today_count": 78, "today": "2026-02-26", "bot_links": {}}