{"links": ["https://pan.quark.cn/s/7d2c6d521506", "https://pan.quark.cn/s/b19e5718d645", "https://pan.quark.cn/s/292fb2a4e30e", "https://www.123684.com/s/MZ4HTd-4BlJv", "https://pan.quark.cn/s/206fc870f383", "https://pan.quark.cn/s/5b126621b148", "https://www.alipan.com/s/i8hghcDnAxx", "https://pan.quark.cn/s/a5ee60fe9e02", "https://pan.quark.cn/s/6a25f7997507", "https://pan.quark.cn/s/c1b21b2c2d58"], "sizes": [7714, 25899, 1225685], "chat_forward_count_msg_id": {"qfsy_tgsearch": 40601}, "today_count": 10, "today": "2025-06-18", "bot_links": {}}