{"links": ["https://pan.quark.cn/s/d8e6fe5f549a", "https://pan.quark.cn/s/cce375b3cad0", "https://pan.quark.cn/s/c28a9bb6ba18", "https://pan.quark.cn/s/52e6fd6e7b5f?pwd=VQAS", "https://pan.quark.cn/s/8e0f8f1262cd", "https://pan.quark.cn/s/95105b4c1b4c", "https://pan.quark.cn/s/d957b8ed911c", "https://pan.quark.cn/s/4800634defc2", "https://pan.quark.cn/s/e21f3d708c6d", "https://pan.quark.cn/s/7c967a711ffe", "https://www.123684.com/s/u9izjv-59UWv", "https://115cdn.com/s/swwiko83wrb?password=a9c8#", "https://pan.quark.cn/s/a80bdc103e6c", "https://pan.quark.cn/s/f57d5126cb4d", "https://pan.quark.cn/s/a8a117384e09", "https://pan.quark.cn/s/e16e537c06ab", "https://www.alipan.com/s/is3spV2Wz2V", "https://pan.quark.cn/s/19a7e78c8be8", "https://pan.quark.cn/s/4974d8c7ca51", "https://pan.quark.cn/s/868bb2bad988", "https://pan.quark.cn/s/d55f3f663011", "https://pan.quark.cn/s/efc4ba4117c4", "https://pan.quark.cn/s/2ac10749fa7f", "https://pan.quark.cn/s/af706b08cbd0", "https://pan.quark.cn/s/9e7a8ecaa0da", "https://pan.quark.cn/s/01f66507f596?pwd=M7QD", "https://pan.quark.cn/s/5702f2126308", "https://pan.quark.cn/s/c3a953ba6e4f", "https://www.123684.com/s/u9izjv-9kUWv", "https://pan.quark.cn/s/fcda1154ad3d", "https://pan.quark.cn/s/3a43281669cd", "https://pan.quark.cn/s/3554d82ebe25", "https://pan.quark.cn/s/97bbb0ba50ed", "https://pan.quark.cn/s/b77279de2368", "https://pan.quark.cn/s/7727bdf4ec99", "https://www.alipan.com/s/C2y5BLHYsr3", "https://pan.quark.cn/s/44a8ea3a7674", "https://pan.quark.cn/s/a10f9c525243", "https://pan.quark.cn/s/e415bd08b484", "https://pan.quark.cn/s/fa1b5bfbf4e4", "https://pan.quark.cn/s/b68ea7b62058", "https://pan.quark.cn/s/fb6649b5faca", "https://cloud.189.cn/t/jUjiueuEfAFf", "https://pan.quark.cn/s/fe09a5a9c94a", "https://pan.quark.cn/s/6a538feee9de", "https://pan.quark.cn/s/209f5f7a2b1f", "https://pan.quark.cn/s/edb426775838", "https://pan.baidu.com/s/1heT0lOKS4GGbpwTypFF2uA?pwd=z7mi", "https://pan.quark.cn/s/c48ac9011193", "https://pan.quark.cn/s/d8fdc0136dd3", "https://pan.quark.cn/s/40bfa6f74983", "https://pan.quark.cn/s/7cbce6fde9c8", "https://pan.quark.cn/s/c9613b482e76?pwd=2Pan", "https://pan.quark.cn/s/db7c72f694f0", "https://pan.quark.cn/s/4cecea4d368e", "https://pan.quark.cn/s/83b3ae177e91", "https://pan.quark.cn/s/aa7299b4682b", "https://pan.quark.cn/s/835d0271d6db", "https://pan.quark.cn/s/4b0ba8d0bee9", "https://cloud.189.cn/t/jyIn2mbIBnu2", "https://pan.quark.cn/s/0c34ea8df07e", "https://pan.quark.cn/s/f85895d855b9", "https://115cdn.com/s/swwikit3wrb?password=i089#", "https://www.123912.com/s/6byjTd-V70t?\u63d0\u53d6\u7801\uff1afgMw", "https://pan.quark.cn/s/c7d317601d91", "https://pan.quark.cn/s/752baf0eca7d", "https://pan.quark.cn/s/573e473da933", "https://pan.quark.cn/s/82d619f02706", "https://pan.quark.cn/s/4e4b4fe026de", "https://pan.quark.cn/s/b15764ae9d5d"], "sizes": [4564], "chat_forward_count_msg_id": {"qfsy_tgsearch": 43444}, "today_count": 70, "today": "2025-06-30", "bot_links": {}}