{"links": ["https://pan.baidu.com/s/1ZHosLZSHya9FzkLy_m5q7Q?pwd=i9w8", "https://pan.quark.cn/s/a1a5cb3dc903", "https://pan.quark.cn/s/1a6f42436dd5", "https://pan.baidu.com/s/1B9EpfMZjSb1rwb8Hpk7T9A?pwd=6666", "https://pan.quark.cn/s/bf372e1423d7", "https://pan.quark.cn/s/25324af7552e", "https://pan.quark.cn/s/89909e657acd", "https://pan.quark.cn/s/cac76730fcae", "https://pan.quark.cn/s/722ae8fcc16c", "https://pan.quark.cn/s/ed654c211468", "https://pan.quark.cn/s/6b1d5e7bfac8", "https://pan.baidu.com/s/19iXFqkWoA6DvnBIwDNYQKg?pwd=pt7j", "https://pan.baidu.com/s/1HC-rB7LEXYEKfcKyJzdS_w?pwd=0a3k", "https://pan.baidu.com/s/1KQT8XOeUq9verguPmHgfrQ?pwd=6666", "https://pan.quark.cn/s/960887c838cb", "https://pan.baidu.com/s/1crfvvGQ3WoR0ufNX3EV3nA?pwd=f3vu", "https://pan.quark.cn/s/d2df219cc1f2", "https://cloud.189.cn/t/EzMNzuNbAnIn", "https://pan.quark.cn/s/1a87b7a8898f", "https://pan.baidu.com/s/1SJfJCQhUuElEK3pWiMsa8g?pwd=tham", "https://pan.baidu.com/s/1P3zOc_AqcLyNb9rR1B-Jog?pwd=76f7", "https://pan.quark.cn/s/3c95cddb265b", "https://pan.baidu.com/s/1cL4dWa9FYFLfSNPRETNsTQ?pwd=sthj", "https://pan.quark.cn/s/024175d478c7", "https://pan.quark.cn/s/097022ac63de", "https://pan.quark.cn/s/d705987ecdf6", "https://pan.quark.cn/s/f2ecad00fc2a", "https://pan.quark.cn/s/d2ad8414bca6", "https://pan.quark.cn/s/ceb000843983", "https://pan.quark.cn/s/a168e4092bb8", "https://pan.quark.cn/s/4590879fd171", "https://pan.quark.cn/s/5e95c6b835f6", "https://pan.baidu.com/s/1Q1MpOVWWHKAIG6JbzABpoQ?pwd=5G2A", "https://pan.quark.cn/s/40c4d56a1a6b", "https://pan.quark.cn/s/8091c40ac3c4", "https://pan.quark.cn/s/9889733ac1c6", "https://pan.quark.cn/s/e17918eefead", "https://www.alipan.com/s/2UZ2BTkz6pH", "https://pan.quark.cn/s/461a9c1437dc", "https://pan.quark.cn/s/746a313d4b25", "https://pan.quark.cn/s/157bd836c089", "https://pan.baidu.com/s/1PDkBK6GuqUeOmu0QzscSmg?pwd=aQ68", "https://pan.baidu.com/s/19sF8BeO_1YUFZ8O-FOVaAg?pwd=pa5h", "https://www.123684.com/s/RWJUVv-aUIq?pwd=ZY4K", "https://www.123684.com/s/RWJUVv-8SIq?pwd=ZY4K#", "https://pan.quark.cn/s/74b21b91b53d", "https://pan.quark.cn/s/b1d3be293034", "https://pan.quark.cn/s/3bc0f3b1e10d", "https://pan.baidu.com/s/1tdcVisBJYT4PbimtlK17yA?pwd=2cw6", "https://pan.quark.cn/s/d022e1891f29", "https://pan.quark.cn/s/df70d33df412", "https://www.123684.com/s/RWJUVv-0SIq?pwd=ZY4K#", "https://cloud.189.cn/t/MruAbmMbEbu2", "https://pan.quark.cn/s/a7199e54cc28", "https://pan.quark.cn/s/0e2e7186f664", "https://www.alipan.com/s/BPTuXSFhKqD", "https://pan.baidu.com/s/1xrHOQ_7OtG7F13z6T2HScQ?pwd=6666", "https://pan.quark.cn/s/cc1b16921b09", "https://pan.baidu.com/s/1F4hT7IN7CTDDHumtF6bIxg?pwd=y6yp", "https://pan.quark.cn/s/6d05823e39fb", "https://pan.quark.cn/s/ed1244b841d1", "https://pan.baidu.com/s/1KdU23LwyZv1dO035IfMeOQ?pwd=ip3y", "https://www.123684.com/s/RWJUVv-6UIq?pwd=ZY4K", "https://pan.quark.cn/s/68ae7fa6ee75", "https://pan.quark.cn/s/5cecfd4fa6a3", "https://drive.uc.cn/s/57cf286039494", "https://pan.quark.cn/s/a67e689f2911", "https://pan.quark.cn/s/9a43feb4d621", "https://pan.quark.cn/s/f9682bdbbc2d", "https://cloud.189.cn/t/iuimYbB7ZrEv", "https://pan.quark.cn/s/c56742b793f9", "https://pan.baidu.com/s/1_zsiCFnI7jPrN96JWiRpRg?pwd=b17L", "https://pan.quark.cn/s/02f8e1a0860f", "https://pan.baidu.com/s/1iUc8X-Ln-1r9gsHE69PjPA?pwd=2bb8", "https://www.123684.com/s/RWJUVv-mSIq?pwd=ZY4K", "https://pan.baidu.com/s/1j-idpP2eR65JIpQfMvToqw?pwd=rCB7", "https://pan.quark.cn/s/086dae1f243c", "https://pan.quark.cn/s/7512448ce9a0"], "sizes": [21161730, 14024387, 38917668, 217832, 17064457, 18488874, 23242317, 30079502, 16074424, 13951769, 18325919], "chat_forward_count_msg_id": {"qfsy_tgsearch": 103503}, "today_count": 78, "today": "2026-03-06", "bot_links": {}}