{"links": ["https://www.alipan.com/s/fGnAdP35tx4", "https://pan.quark.cn/s/50197f3fac24", "https://pan.quark.cn/s/b745ecec60cc", "https://pan.quark.cn/s/c4c086f766a6", "https://pan.quark.cn/s/7424dd8e4a13", "https://www.alipan.com/s/mMsT1tA6aV3", "https://anxia.com/s/swhec483z97?password=ga60", "https://pan.quark.cn/s/b3b166c883a9", "https://pan.quark.cn/s/19c5478bc667", "https://pan.quark.cn/s/dfcbbaad5859", "https://pan.quark.cn/s/3f41eee9f597", "https://pan.quark.cn/s/b771743dedfc", "https://pan.quark.cn/s/1bc0504c85e2", "https://pan.quark.cn/s/7ee05504d2b3", "https://pan.quark.cn/s/f4450dd80a82", "https://drive.uc.cn/s/8bd65845b39b4?public=1", "https://pan.quark.cn/s/fa10eea8b6ff", "https://pan.quark.cn/s/b1d15cc148b7", "https://pan.quark.cn/s/5c95abc82e8f", "https://pan.quark.cn/s/bd2acaefbc1c", "https://pan.quark.cn/s/c07a9cf1f314", "https://pan.quark.cn/s/d75b8a3c820d"], "sizes": [], "chat_forward_count_msg_id": {"qfsy_tgsearch": 15580}, "today_count": 22, "today": "2025-02-06", "bot_links": {"get1738843347BE8B6C": "https://www.alipan.com/s/7DzFT3fWDvq", "get1738843487160043": "https://www.alipan.com/s/UqyhLy2iYkK", "get17388435021C7174": "https://www.alipan.com/s/7G4zwjj9pu8"}}