{"links": ["https://pan.quark.cn/s/dcae12745581", "https://pan.quark.cn/s/c94823ffe84f", "https://pan.quark.cn/s/7115d5d9a7b4", "https://pan.quark.cn/s/ccff6f93c6ef", "https://pan.baidu.com/s/1k4Hg6P4cqN_TLbMs62xzRQ?pwd=3dsy", "https://yun.139.com/shareweb/#/w/i/2w2KMktAXGkb8", "https://pan.quark.cn/s/8436d0e97638", "https://pan.baidu.com/s/1rAR7cEnF2H-uyEkk-dvpRg?pwd=vp3k", "https://pan.quark.cn/s/21d9f13e58b9", "https://www.123pan.com/s/IpPUVv-yFuvv?pwd=Ocat", "https://pan.quark.cn/s/8b80ed0a4f88", "https://drive.uc.cn/s/f17111d045a44", "https://pan.quark.cn/s/2d2f7b13a255", "https://pan.baidu.com/s/1qVlf19Y2rcSZWyY4I_G76g?pwd=upa2", "https://pan.baidu.com/s/1KB-OZMjUGSo_Jaxvh-3EEA?pwd=BXS5", "https://pan.quark.cn/s/ff1e5553ea85", "https://pan.quark.cn/s/e94a230e4013", "https://www.alipan.com/s/eaoaGp7d4BJ", "https://115cdn.com/s/swslm8y33xj?password=v6a6", "https://pan.quark.cn/s/63f70296244c", "https://pan.quark.cn/s/e7e04475ebd4", "https://pan.quark.cn/s/42a8ab1ec448", "https://pan.quark.cn/s/089f928ad62e", "https://pan.baidu.com/s/1131X7BtIldblpmnW-zIe5w?pwd=dbns", "https://pan.quark.cn/s/e30ab5d2edf3", "https://pan.quark.cn/s/3b2e01e4129c", "https://115cdn.com/s/swsl6gb33xj?password=k687", "https://pan.quark.cn/s/34d2dcd70144", "https://pan.quark.cn/s/66fff63ce12b", "https://www.alipan.com/s/R3TzXoKPAVA", "https://pan.quark.cn/s/bf837b255faf", "https://115cdn.com/s/swsl79d33xj?password=a8b7", "https://www.alipan.com/s/QctbWAM6pDx", "https://pan.baidu.com/s/1cj-qRfdAYKX71csBTDzlVA?pwd=4A1C", "https://pan.quark.cn/s/58418d398153", "https://pan.quark.cn/s/1ea7f10cbd1c", "https://pan.quark.cn/s/404e70167499", "https://pan.quark.cn/s/2d5b9dd877f8", "https://pan.quark.cn/s/ee64cd0e364c", "https://pan.quark.cn/s/b2ec4e0d3e58", "https://115cdn.com/s/swslm0e3nbi?password=8888", "https://www.alipan.com/s/hLG6Zkmvtip", "https://www.123pan.com/s/IpPUVv-U1evv?pwd=Ocat", "https://www.123pan.com/s/IpPUVv-Eehdv?pwd=Ocat", "https://pan.baidu.com/s/1HqTERYFVDvkWUs8QeEmAcQ?pwd=Yu66", "https://pan.quark.cn/s/488edb1252f8", "https://www.123pan.com/s/IpPUVv-3rmdv?pwd=Ocat", "https://www.123pan.com/s/IpPUVv-qTyvv?pwd=Ocat", "magnet:?xt=urn:btih:76d427665256309abd41ce8a8dc4a409637e7037", "https://pan.quark.cn/s/eda666a5465a", "https://115cdn.com/s/swslmei33xj?password=x106", "https://115cdn.com/s/swslm8n33xj?password=sf71", "https://pan.baidu.com/s/1fhN6fZpRAWQFR7PUjaWi9A?pwd=4v28", "https://pan.quark.cn/s/fcb2d30400c9", "https://pan.baidu.com/s/1KWOsjM8uYi4FoVLbmu_tNQ?pwd=5qpe", "https://115cdn.com/s/swslity3nbi?password=8888", "https://pan.quark.cn/s/acfa7b3ff8f7", "https://115cdn.com/s/swsl6gt33xj?password=u098", "https://yun.139.com/shareweb/#/w/i/2w2KLjp7Qpdvo", "https://pan.quark.cn/s/0d80619a89b3", "https://pan.quark.cn/s/844be0ebf8bc", "https://www.123pan.com/s/IpPUVv-o8edv?pwd=Ocat", "https://www.alipan.com/s/roshcbuaYvU", "https://pan.quark.cn/s/f0d738946b81", "https://pan.quark.cn/s/e8db422c0dc0", "https://pan.quark.cn/s/b22d4e151afc", "https://pan.quark.cn/s/cc309e3a5cab", "https://pan.quark.cn/s/c973421ad70e", "https://pan.quark.cn/s/fe9066def1da", "https://115cdn.com/s/swsln7333xj?password=m082", "https://pan.baidu.com/s/1q6lfNU8eF7Axyb_zRzHWjA?pwd=a5ng", "https://www.alipan.com/s/LX4jTvC4Khf", "https://pan.baidu.com/s/1hbM66LHjzS4G1G_O88oltA?pwd=Yu66", "https://www.alipan.com/s/YwkXvigqGjH", "https://yun.139.com/shareweb/#/w/i/2w2KM2sfKZ4oa", "https://pan.quark.cn/s/67885dfeeea7", "https://pan.baidu.com/s/1oRE69RGDI8tjRvCM7Uf-1A?pwd=j35d", "https://pan.quark.cn/s/df0e2925bf5a", "https://115cdn.com/s/swsl7p233xj?password=i465", "https://pan.quark.cn/s/d2a20860d09c", "https://pan.quark.cn/s/fff747f132d4", "https://drive.uc.cn/s/8cb2d1a073074", "https://pan.quark.cn/s/046b4c1e7ddb", "https://pan.quark.cn/s/9a314e7cb979", "https://drive.uc.cn/s/835b193a30784", "https://www.123pan.com/s/IpPUVv-5Tyvv?pwd=Ocat", "https://pan.quark.cn/s/2da0d999ebea", "https://www.alipan.com/s/BDaBRuJ2xrG", "https://pan.quark.cn/s/69a20be82d12", "https://pan.quark.cn/s/156e6d788916", "https://115cdn.com/s/swslmef3nbi?password=8888", "https://pan.quark.cn/s/7e0ea1db5ec1", "https://pan.baidu.com/s/1A4XW9xj2N_Ykwl3YVS-5Jg?pwd=i6qg"], "sizes": [41253249, 20055939, 19347204, 46581895, 2415006, 6930336, 13869861, 12240305, 7523000, 6745018, 35467843, 10943045, 97234631, 22732235, 491087, 20070610, 40047322, 21118174, 1322207, 13071713, 21279210, 12196330, 46380915, 48604404, 38582774, 10384120], "chat_forward_count_msg_id": {"qfsy_tgsearch": 131373}, "today_count": 93, "today": "2026-07-05", "bot_links": {}}