{"links": ["https://pan.quark.cn/s/935a3ee571b9", "https://pan.baidu.com/s/1ojcmZ3I949xn58lGuOJUog?pwd=xqw4", "https://www.alipan.com/s/nhHqNZYUcvh", "https://pan.quark.cn/s/9b2b088c1257", "https://pan.quark.cn/s/b3c3e4ce36cb", "https://pan.baidu.com/s/1Y-eTqw0ABSNMMNzSieLt_g?pwd=6666", "https://pan.baidu.com/s/1hX9lU1AmqwA3t4xRW5u66g?pwd=kej7", "https://pan.quark.cn/s/01f4bc5eaa7f", "https://pan.baidu.com/s/1afr4mkp3MwV2D_XKgN43rw?pwd=c62w", "https://pan.quark.cn/s/b335e57ec811", "https://cloud.189.cn/t/BNna6jMzE3u2", "https://www.alipan.com/s/hKyNsw5SbVb", "https://pan.baidu.com/s/1sYv9A8rB6xTqdou7ME0aVA?pwd=nyea", "https://pan.quark.cn/s/52e3eaffbf27", "https://pan.quark.cn/s/cd76fc5dafcd", "https://pan.quark.cn/s/f9603c25abd5", "https://pan.quark.cn/s/1a88a0e455ad", "https://pan.baidu.com/s/1BLUGaUzo3leJETGm-iNJWA?pwd=Fa2h"], "sizes": [948147455, 42110239, 339310277, 217832, 8654377, 1056936143, 1155970447, 8052850, 344584402, 398365684, 164828148, 57920472, 103170299, 2265340, 1152848159], "chat_forward_count_msg_id": {"qfsy_tgsearch": 97866}, "today_count": 18, "today": "2026-02-01", "bot_links": {}}