{"links": ["https://pan.baidu.com/s/1u4l1rgQIRTx4s_9I5S4XEQ?pwd=a65z", "https://pan.baidu.com/s/1CutA-yH2bMNNcQ6abz5Hdg?pwd=wrv4", "https://pan.quark.cn/s/29e2f3430860", "https://pan.quark.cn/s/b51790f05912", "https://pan.baidu.com/s/1DoXMdh2iGqUbt1epFf3_3A?pwd=D65H", "https://pan.quark.cn/s/187f6526e6bb", "https://pan.quark.cn/s/d59228b5818d", "https://pan.quark.cn/s/4ee3da0ffb8b", "https://pan.baidu.com/s/1NqVuLDU0FenVZlGtWnmPhw?pwd=14C6", "https://pan.quark.cn/s/aaed0bbacd16", "https://pan.quark.cn/s/36cc02c9ff87", "https://pan.baidu.com/s/1iGzZ9ECIcUeudi_I5r0hiA?pwd=s6jo", "https://pan.baidu.com/s/1CN_t29CUT_e8JbERk9053Q?pwd=1111", "https://cloud.189.cn/t/26zAVjfUbiQf", "https://pan.quark.cn/s/0bb5eef66484", "https://pan.baidu.com/s/1OASVug6m0p5VP5qy-wZYLg?pwd=5122", "https://pan.baidu.com/s/1Ilj03aAw9TVp2d6gnUjNvw?pwd=8p9a", "https://pan.quark.cn/s/35e45da45af8", "https://pan.quark.cn/s/fc8d46d8516f", "https://drive.uc.cn/s/0e02ccc237e44?public=1", "https://pan.quark.cn/s/dcc9f60ad69c", "https://drive.uc.cn/s/e9a6267f5b114?public=1", "https://pan.baidu.com/s/1w_pL1QU_BpiGnZksaYyKaA?pwd=5362", "https://cloud.189.cn/t/QjYNRbYBviiu", "https://pan.quark.cn/s/3cde739ac965", "https://pan.quark.cn/s/c34fe45618fd", "https://cloud.189.cn/t/eQRjyqaMfEBj", "https://pan.quark.cn/s/4f929e42d668", "https://pan.baidu.com/s/1me0xj2kVSBSp4ON6JGbmVA?pwd=6666", "https://cloud.189.cn/t/Rnqyq2FRNvE3", "https://drive.uc.cn/s/f2a6cc5f5ce74", "https://pan.quark.cn/s/6b693a1788c7", "https://pan.quark.cn/s/d400ffd7a646", "https://pan.quark.cn/s/4817b1a43f90", "https://www.alipan.com/s/15aWWtgKGm7", "https://cloud.189.cn/t/RJbiQfRJJB3a", "https://drive.uc.cn/s/a1c946e182964", "https://pan.quark.cn/s/0dcbb52a3386", "https://pan.quark.cn/s/d97528ac2e9f", "https://pan.quark.cn/s/79a007105a88", "https://pan.xunlei.com/s/VOcKLATNk54SHSJnliJAaLyeA1?pwd=ap47#", "https://drive.uc.cn/s/12596dbe756a4", "https://pan.quark.cn/s/abc4d9c36168", "https://pan.quark.cn/s/4f18d51e3fcf", "https://pan.quark.cn/s/9ce4a5622e1b", "https://pan.quark.cn/s/ed267e08ba50", "https://pan.quark.cn/s/1980b09f68af", "https://drive.uc.cn/s/5cc2fc7b79104?public=1", "https://pan.quark.cn/s/b1e0bf4fb891", "https://pan.quark.cn/s/4a230f255f8c", "https://pan.quark.cn/s/958bb5d1c8bd", "https://pan.quark.cn/s/be4d2e1f5ea6", "https://pan.baidu.com/s/1CpcEYiL_tA8nsIYbXNCL3A?pwd=48j4", "https://pan.baidu.com/s/1VdEY4R3NQOqE8k0hV5SFMQ?pwd=tj5n", "https://pan.baidu.com/s/1HqXXQ1iRMEtR9I7GvRFYIA?pwd=fpux", "https://pan.baidu.com/s/1uaPWaCSt6Q4HioWFG6Sfng?pwd=1023", "https://pan.baidu.com/s/1iKQDPF8I5ghjFD9hbXspNw?pwd=0628", "https://cloud.189.cn/t/6vauqq3yEFry", "https://pan.baidu.com/s/1RwG2H3MJMm5oKYk-sltUaw?pwd=edeP", "https://pan.quark.cn/s/f33d92ed76bd", "https://pan.quark.cn/s/0f7786785e96", "https://pan.baidu.com/s/1rJoRLR5RnnfSaxYmD-JmDQ?pwd=v98p", "https://pan.quark.cn/s/3f436ad3fc94", "https://pan.quark.cn/s/62e5226f27d6", "https://pan.baidu.com/s/1qxWug_1T5dS04DFXzIaCvg?pwd=766v", "https://pan.quark.cn/s/26be274c29d8", "https://www.alipan.com/s/bjefgkt3sSt", "https://pan.baidu.com/s/1uIMWaMfb_k8V6cxtH9HDCw?pwd=Yu66", "https://t.me/aibox2048_bot?start=cl_qixingzhenren", "https://pan.quark.cn/s/56d902781e69", "https://pan.quark.cn/s/f39806b3cc93", "https://pan.baidu.com/s/1OkJ00KeL3pPf5Qmc_jKPkA?pwd=6666", "https://drive.uc.cn/s/7f65462ba0a54", "https://pan.quark.cn/s/ea6eba9e213a", "https://pan.quark.cn/s/0d47706ca976", "https://pan.quark.cn/s/2d9a773e7b47", "https://cloud.189.cn/t/iqeeyerUBbYn", "https://pan.quark.cn/s/69f507d212b6", "https://pan.baidu.com/s/18hvm9hpP4TyvcAq34uwDZQ?pwd=54z3", "https://pan.quark.cn/s/ac6773d62d83", "https://pan.quark.cn/s/e616920dd55e", "https://pan.quark.cn/s/141095f33c46", "https://pan.baidu.com/s/17LZoClOY4OUDSELNJdT9Jg?pwd=mPS8", "https://www.alipan.com/s/KcKky3E7Lpg", "https://pan.baidu.com/s/1Wk-Wn7dCZJhNXK6elHoe7Q?pwd=j465", "https://pan.quark.cn/s/2498fb44027a", "https://pan.quark.cn/s/8708f2fe72f1", "https://pan.quark.cn/s/d85824d86146", "https://pan.quark.cn/s/4ce165cdd423", "https://pan.baidu.com/s/1rHyZ9XRGgpUQrMnl9dvcMw?pwd=Yu66", "https://pan.quark.cn/s/873745ceb60e", "https://pan.quark.cn/s/2f00a6778590", "https://pan.quark.cn/s/c163797f1268", "https://www.123684.com/s/u9izjv-kvUWv", "https://pan.quark.cn/s/9be108de5b87"], "sizes": [], "chat_forward_count_msg_id": {"qfsy_tgsearch": 75851}, "today_count": 95, "today": "2025-10-30", "bot_links": {"cl_qixingzhenren": "https://t.me/aibox2048_bot?start=cl_qixingzhenren", "get_link_7742359132_1761757310_baidu": "https://pan.baidu.com/s/1iGzZ9ECIcUeudi_I5r0hiA?pwd=s6jo", "get_link_7742359132_1761757310_xunlei": "https://pan.xunlei.com/s/VOc-bQXIZlu_xmIWc8rQpgaAA1?pwd=fimc#", "get_link_1813656985_1761757554_quark": "https://pan.quark.cn/s/56d902781e69", "get_link_1813656985_1761757554_baidu": "https://pan.baidu.com/s/1HqXXQ1iRMEtR9I7GvRFYIA?pwd=fpux", "get_link_1813656985_1761757810_quark": "https://pan.quark.cn/s/ed267e08ba50", "get_link_1813656985_1761757810_baidu": "https://pan.baidu.com/s/1RwG2H3MJMm5oKYk-sltUaw?pwd=edeP", "get_link_1813656985_1761758014_quark": "https://pan.quark.cn/s/141095f33c46", "get_link_1813656985_1761758014_baidu": "https://pan.baidu.com/s/1DoXMdh2iGqUbt1epFf3_3A?pwd=D65H", "get_link_1813656985_1761758213_quark": "https://pan.quark.cn/s/69f507d212b6", "get_link_1813656985_1761758213_baidu": "https://pan.baidu.com/s/1w_pL1QU_BpiGnZksaYyKaA?pwd=5362", "get_link_1813656985_1761758918_quark": "https://pan.quark.cn/s/2498fb44027a", "get_link_1813656985_1761758918_baidu": "https://pan.baidu.com/s/1NqVuLDU0FenVZlGtWnmPhw?pwd=14C6", "get_link_501930165_1761778326_quark": "https://pan.quark.cn/s/d400ffd7a646", "get_link_501930165_1761778402_quark": "https://pan.quark.cn/s/2f00a6778590", "get_link_8024972825_1761785260_quark": "https://pan.quark.cn/s/62e5226f27d6", "get_link_8024972825_1761785315_quark": "https://pan.quark.cn/s/4f929e42d668", "get_link_8024972825_1761785395_quark": "https://pan.quark.cn/s/1980b09f68af", "get_link_8024972825_1761785458_quark": "https://pan.quark.cn/s/36cc02c9ff87", "get_link_8024972825_1761785529_quark": "https://pan.quark.cn/s/79a007105a88", "get_link_8024972825_1761785587_quark": "https://pan.quark.cn/s/72f3d54377e3", "get_link_8024972825_1761785658_quark": "https://pan.quark.cn/s/29e2f3430860", "get_link_8024972825_1761786043_quark": "https://pan.quark.cn/s/ba20526f55c7", "get_link_404904764_1761786386_quark": "https://pan.quark.cn/s/9be108de5b87", "get_link_404904764_1761786386_baidu": "https://pan.baidu.com/s/1CN_t29CUT_e8JbERk9053Q?pwd=1111", "get_link_404904764_1761786386_xunlei": "https://pan.xunlei.com/s/VOab3AwK8mFV8iQP_UrH3T4uA1?pwd=aqwz#", "get_link_7275802881_1761744274_aliyun": "https://www.alipan.com/s/15aWWtgKGm7", "get_link_7275802881_1761748533_aliyun": "https://www.alipan.com/s/bjefgkt3sSt", "get_link_7275802881_1761748870_aliyun": "https://www.alipan.com/s/Dafm3hbnBB1"}}